redelex/__init__.py
redelex/datasets/__init__.py
redelex/datasets/ctu_dataset.py
redelex/datasets/ctu_datasets.py
redelex/datasets/dataset-info.csv
redelex/datasets/db_dataset.py
redelex/db/__init__.py
redelex/db/column_types.py
redelex/db/db_inspector.py
redelex/nn/__init__.py
redelex/nn/corruptors.py
redelex/nn/losses.py
redelex/nn/encoders/__init__.py
redelex/nn/encoders/linear_row_encoder.py
redelex/nn/encoders/per_feature_row_encoder.py
redelex/nn/layers/__init__.py
redelex/nn/layers/attention.py
redelex/nn/loaders/__init__.py
redelex/nn/loaders/hgt_multi_input_loader.py
redelex/nn/models/__init__.py
redelex/nn/models/dbformer.py
redelex/nn/models/pretrain_wrappers.py
redelex/nn/models/rdl_model.py
redelex/nn/models/sagegnn.py
redelex/nn/models/tabular.py
redelex/nn/models/rgnn/__init__.py
redelex/nn/models/rgnn/dbformer.py
redelex/tasks/__init__.py
redelex/tasks/ctu_entity_task_base.py
redelex/tasks/ctu_entity_task_classic.py
redelex/tasks/ctu_entity_task_temporal.py
redelex/tasks/ctu_link_task.py
redelex/tasks/ctu_tasks.py
redelex/tasks/task-info.csv
redelex/utils/__init__.py
redelex/utils/autodetect_schema.py
redelex/utils/datetime.py
redelex/utils/merge.py
redelex-0.5.1.dist-info/licenses/LICENSE
redelex-0.5.1.dist-info/WHEEL
redelex-0.5.1.dist-info/METADATA
redelex-0.5.1.dist-info/RECORD
