Metadata-Version: 2.4
Name: redelex
Version: 0.5.1
Summary: ReDeLEx: A Framework for Relational Deep Learning Exploration
Keywords: 
Author-email: Jakub Peleška <jakub.peleska@fel.cvut.cz>
Requires-Python: >=3.12
Classifier: License :: OSI Approved :: MIT License
License-File: LICENSE
Requires-Dist: relbench>=1.1.0
Requires-Dist: pandas>=2.2.3
Requires-Dist: pymysql>=1.1.1
Requires-Dist: sqlalchemy>=2.0.40
Requires-Dist: inflect>=7.5.0
Requires-Dist: tqdm>=4.67.1
Requires-Dist: attrs>=25.3.0
Project-URL: Homepage, https://github.com/jakubpeleska/ctu-relational-py
Project-URL: Issues, https://github.com/jakubpeleska/ctu-relational-py/issues
